EffectiveHalos/Cosmology.py
EffectiveHalos/CountsCovariance.py
EffectiveHalos/HaloModel.py
EffectiveHalos/HaloPhysics.py
EffectiveHalos/MassFunction.py
EffectiveHalos/MassIntegrals.py
EffectiveHalos/__init__.py
EffectiveHalos-1.1.0.dist-info/LICENSE
EffectiveHalos-1.1.0.dist-info/METADATA
EffectiveHalos-1.1.0.dist-info/WHEEL
EffectiveHalos-1.1.0.dist-info/top_level.txt
EffectiveHalos-1.1.0.dist-info/RECORD
