Metadata-Version: 2.1
Name: EffectiveHalos
Version: 1.1.0
Summary: Combining the Halo Model and Perturbation Theory: A 1% Accurate Model to k = 1 h/Mpc
Home-page: https://effectivehalos.rtfd.io
Author: Oliver Philcox
Author-email: ohep2@cantab.ac.uk
License: UNKNOWN
Platform: UNKNOWN
Classifier: Programming Language :: Python :: 2
Classifier: Programming Language :: Python :: 3
Classifier: License :: OSI Approved :: MIT License
Classifier: Operating System :: OS Independent
Requires-Dist: numpy
Requires-Dist: scipy
Requires-Dist: matplotlib
Requires-Dist: mcfit
Requires-Dist: fast-pt
